sg
tests
