Metadata-Version: 1.0
Name: sg
Version: 0.0.4
Summary: UNKNOWN
Home-page: UNKNOWN
Author: takada-at
Author-email: takada-at@klab.com
License: UNKNOWN
Platform: UNKNOWN
